designs/rns_mrc/src/rns_mrc_recon.v
`timescale 1ns/1ps

module rns_mrc_recon #(
    parameter W0        = 2,
    parameter W1        = 3,
    parameter W2        = 3,
    parameter W3        = 4,
    parameter OUT_WIDTH = 16
)(
    input  wire                 clk,
    input  wire                 rst_n,
    input  wire                 MRC_Start,
    input  wire [W0-1:0]        r0,
    input  wire [W1-1:0]        r1,
    input  wire [W2-1:0]        r2,
    input  wire [W3-1:0]        r3,
    output reg  [OUT_WIDTH-1:0] X_out,
    output reg                  MRC_Done
);

    localparam integer MOD0      = 3;
    localparam integer MOD1      = 5;
    localparam integer MOD2      = 7;
    localparam integer MOD3      = 11;

    localparam integer MPREV1    = 3;
    localparam integer MPREV2    = 15;
    localparam integer MPREV3    = 105;
    localparam integer M_TOTAL   = 1155;

    localparam integer INV_12    = 2; // inv(3 mod 5)
    localparam integer INV_123   = 1; // inv(15 mod 7)
    localparam integer INV_1234  = 2; // inv(105 mod 11)

    localparam [2:0]
        S_IDLE = 3'd0,
        S_S1   = 3'd1,
        S_S2   = 3'd2,
        S_S3   = 3'd3,
        S_S4   = 3'd4,
        S_DONE = 3'd5;

    reg [2:0] state;

    reg start_d;
    wire start_pulse = MRC_Start & ~start_d;

    reg [1:0] r0_mod_r;
    reg [2:0] r1_mod_r;
    reg [2:0] r2_mod_r;
    reg [3:0] r3_mod_r;

    reg [1:0] X1_r;   // 0..2
    reg [3:0] X2_r;   // 0..14
    reg [6:0] X3_r;   // 0..104

    function integer norm_mod;
        input integer x;
        input integer m;
        integer t;
        begin
            t = x % m;
            if (t < 0)
                t = t + m;
            norm_mod = t;
        end
    endfunction

    wire [2:0]  t2_w;
    wire [3:0]  X2_next_w;
    wire [2:0]  t3_w;
    wire [6:0]  X3_next_w;
    wire [3:0]  t4_w;
    wire [10:0] X4_w;
    wire [10:0] total_mod_w;

    assign t2_w        = norm_mod(norm_mod(r1_mod_r - norm_mod(X1_r, MOD1), MOD1) * INV_12, MOD1);
    assign X2_next_w   = X1_r + (t2_w * MPREV1);

    assign t3_w        = norm_mod(norm_mod(r2_mod_r - norm_mod(X2_r, MOD2), MOD2) * INV_123, MOD2);
    assign X3_next_w   = X2_r + (t3_w * MPREV2);

    assign t4_w        = norm_mod(norm_mod(r3_mod_r - norm_mod(X3_r, MOD3), MOD3) * INV_1234, MOD3);
    assign X4_w        = X3_r + (t4_w * MPREV3);

    assign total_mod_w = norm_mod(X4_w, M_TOTAL);

    always @(posedge clk) begin
        if (!rst_n) begin
            state    <= S_IDLE;
            start_d  <= 1'b0;
            MRC_Done <= 1'b0;
        end else begin
            start_d  <= MRC_Start;
            MRC_Done <= 1'b0;

            case (state)
                S_IDLE: begin
                    if (start_pulse) begin
                        r0_mod_r <= norm_mod(r0, MOD0);
                        r1_mod_r <= norm_mod(r1, MOD1);
                        r2_mod_r <= norm_mod(r2, MOD2);
                        r3_mod_r <= norm_mod(r3, MOD3);
                        state    <= S_S1;
                    end
                end

                S_S1: begin
                    X1_r  <= r0_mod_r;
                    state <= S_S2;
                end

                S_S2: begin
                    X2_r  <= X2_next_w;
                    state <= S_S3;
                end

                S_S3: begin
                    X3_r  <= X3_next_w;
                    state <= S_S4;
                end

                S_S4: begin
                    X_out <= total_mod_w;
                    state <= S_DONE;
                end

                S_DONE: begin
                    MRC_Done <= 1'b1;
                    state    <= S_IDLE;
                end

                default: begin
                    state <= S_IDLE;
                end
            endcase
        end
    end

endmodule

designs/rns_mrc/src/rns_slice.v
`timescale 1ns/1ps

// Function: Per-Modulus RNS ALU Slice (ADD / SUB / MUL)
// Hardware counterpart of Python per-channel ops in ops.py:
//   add(a, b, m) = (a + b) % m
//   sub(a, b, m) = (a - b) % m
//   mul(a, b, m) = (a * b) % m

// Data Path: Stage 3 – Modular ALUs
// Control:
//   - CU asserts ALU_EN (start operation for the specific slice)
//   - Slice asserts ALU_Done HIGH exactly one cycle later (Handshake)

// Operation Select (op_sel):
//   2'b00 : ADD
//   2'b01 : SUB
//   2'b10 : MUL
//   others: result = 0

module rns_slice #(
    parameter MODULUS = 3,
    parameter WIDTH   = 2
)(
    input  wire                 clk,
    input  wire                 rst_n,
    input  wire                 ALU_EN,
    input  wire [1:0]           op_sel,
    input  wire [WIDTH-1:0]     a,
    input  wire [WIDTH-1:0]     b,
    output reg  [WIDTH-1:0]     y,
    output reg                  ALU_Done
);

    reg [WIDTH-1:0] y_next;
    reg             start_d;
    integer         tmp;

    always @* begin
        y_next = {WIDTH{1'b0}};
        tmp    = 0;

        case (op_sel)
            2'b00: begin
                tmp    = a + b;
                tmp    = tmp % MODULUS;
                y_next = tmp[WIDTH-1:0];
            end

            2'b01: begin
                tmp    = a + MODULUS - b;
                tmp    = tmp % MODULUS;
                y_next = tmp[WIDTH-1:0];
            end

            2'b10: begin
                tmp    = a * b;
                tmp    = tmp % MODULUS;
                y_next = tmp[WIDTH-1:0];
            end

            default: begin
                y_next = {WIDTH{1'b0}};
            end
        endcase
    end

    always @(posedge clk) begin
        if (!rst_n) begin
            start_d  <= 1'b0;
            ALU_Done <= 1'b0;
        end else begin
            ALU_Done <= start_d;
            start_d  <= ALU_EN;

            if (ALU_EN)
                y <= y_next;
        end
    end

endmodule

designs/rns_crt/src/rns_encoder.v
`timescale 1ns/1ps

// Function: Forward Conversion (Binary → Residues)
// Hardware counterpart of Python encode(): encode(x, [3, 5, 7, 11])

// Data Path: Stage 2 – Encoder Bank
// Control:
//   - CU asserts Encode_EN
//   - Encoder outputs Encode_Done high for 1 cycle
// Moduli Set: M0 = 3, M1 = 5, M2 = 7, M3 = 11

// Notes:
//   - Unsigned domain only (x ≥ 0).
//   - One-cycle latency.
//   - Modulus operations are constant-mod (synthesizable)
//   - Reset is kept on handshake only; residue outputs are not reset

module rns_encoder #(
    parameter WIDTH_IN = 16,
    parameter M0 = 3,
    parameter M1 = 5,
    parameter M2 = 7,
    parameter M3 = 11,
    parameter W0 = 2,
    parameter W1 = 3,
    parameter W2 = 3,
    parameter W3 = 4
)(
    input  wire                 clk,
    input  wire                 rst_n,
    input  wire                 Encode_EN,
    input  wire [WIDTH_IN-1:0]  x,
    output reg                  Encode_Done,
    output reg [W0-1:0]         r0,
    output reg [W1-1:0]         r1,
    output reg [W2-1:0]         r2,
    output reg [W3-1:0]         r3
);

    wire [W0-1:0] r0_next;
    wire [W1-1:0] r1_next;
    wire [W2-1:0] r2_next;
    wire [W3-1:0] r3_next;

    assign r0_next = x % M0;
    assign r1_next = x % M1;
    assign r2_next = x % M2;
    assign r3_next = x % M3;

    always @(posedge clk) begin
        if (!rst_n) begin
            Encode_Done <= 1'b0;
        end else begin
            Encode_Done <= 1'b0;

            if (Encode_EN) begin
                r0 <= r0_next;
                r1 <= r1_next;
                r2 <= r2_next;
                r3 <= r3_next;
                Encode_Done <= 1'b1;
            end
        end
    end

endmodule

designs/rns_crt/src/rns_cu.v
// Function: Control Unit for RNS ALU (CU FSM)

// Controls the pipeline: 
//   IDLE -> LOAD -> ENCODE -> ALU -> RECON -> OUT -> DONE

// Controls:
//   - rns_encoder.v   (Encode_EN / Encode_Done)
//   - rns_slice.v     (ALU_EN / ALU_Done)
//   - rns_crt_recon.v (CRT_Start / CRT_Done)
//   - rns_mrc_recon.v (MRC_Start / MRC_Done)

// Reconstruction Selection (runtime):
//   Recon_Mode = 0 -> use CRT
//   Recon_Mode = 1 -> use MRC

`timescale 1ns/1ps

module rns_cu (
    // Clock & Reset
    input  wire clk,
    input  wire rst_n,

    // External control
    input  wire Start,         // Start a new operation
    input  wire Recon_Mode,    // 0 = CRT, 1 = MRC
    output reg  Done,          // High when full operation completed
    output wire [2:0] CU_state_dbg, // Debug: Current CU FSM state

    // Handshakes from Data Path
    input  wire Encode_Done,   // Encoders finished
    input  wire ALU_Done,      // All ALU slices finished
    input  wire CRT_Done,      // CRT reconstructor finished
    input  wire MRC_Done,      // MRC reconstructor finished

    // Control outputs to Data Path 
    output reg  Load_IN,       // Latch A, B, OpSel into input regs
    output reg  Encode_EN,     // Enable encoders
    output reg  ALU_EN,        // Enable modular ALUs
    output reg  CRT_Start,     // Trigger CRT reconstruction
    output reg  MRC_Start,     // Trigger MRC reconstruction
    output reg  Out_EN         // Latch final X_out register
);

    // State Encoding
    localparam [2:0]
        S_IDLE   = 3'd0,
        S_LOAD   = 3'd1,
        S_ENCODE = 3'd2,
        S_ALU    = 3'd3,
        S_RECON  = 3'd4,
        S_OUT    = 3'd5,
        S_DONE   = 3'd6;

    reg [2:0] state, next_state;

    // State Register
    always @(posedge clk) begin
        if (!rst_n)
            state <= S_IDLE;
        else
            state <= next_state;
    end

    // Next-State Logic
    wire recon_done_sel;
    assign recon_done_sel = (Recon_Mode == 1'b0) ? CRT_Done : MRC_Done;

    always @* begin
        next_state = state; // Default hold

        case (state)
            S_IDLE:   if (Start)       next_state = S_LOAD;
            S_LOAD:                    next_state = S_ENCODE;
            S_ENCODE: if (Encode_Done) next_state = S_ALU;
            S_ALU:    if (ALU_Done)    next_state = S_RECON;
            S_RECON:  if (recon_done_sel) next_state = S_OUT;
            S_OUT:                     next_state = S_DONE;
            S_DONE:   if (!Start)      next_state = S_IDLE;
            default:                   next_state = S_IDLE;
        endcase
    end

    // Output Logic (Moore FSM)
    always @* begin
        // Default all controls LOW
        Load_IN   = 1'b0;
        Encode_EN = 1'b0;
        ALU_EN    = 1'b0;
        CRT_Start = 1'b0;
        MRC_Start = 1'b0;
        Out_EN    = 1'b0;
        Done      = 1'b0;

        case (state)
            S_LOAD:   Load_IN   = 1'b1;
            S_ENCODE: Encode_EN = 1'b1;
            S_ALU:    ALU_EN    = 1'b1;

            S_RECON: begin
                if (Recon_Mode == 1'b0)
                    CRT_Start = 1'b1;
                else
                    MRC_Start = 1'b1;
            end

            S_OUT:  Out_EN = 1'b1;
            S_DONE: Done   = 1'b1;
        endcase
    end

    // Expose internal state for debugging
    assign CU_state_dbg = state;

endmodule

designs/rns_mrc/src/rns_top_mrc.v
`timescale 1ns/1ps

// MRC-only Top-Level RNS ALU
// Structurally aligned to CRNS wrapper style:
// - direct Load_IN capture
// - no datapath async reset
// - unused CRT_Done tied low

module rns_top_mrc #(
    parameter WIDTH_IN  = 16,
    parameter M0 = 3,
    parameter M1 = 5,
    parameter M2 = 7,
    parameter M3 = 11,
    parameter W0 = 2,
    parameter W1 = 3,
    parameter W2 = 3,
    parameter W3 = 4
)(
    input  wire                 clk,
    input  wire                 rst_n,
    input  wire                 Start,
    input  wire [1:0]           Op_Sel,
    input  wire [WIDTH_IN-1:0]  A_in,
    input  wire [WIDTH_IN-1:0]  B_in,
    output wire                 Done,
    output wire [WIDTH_IN-1:0]  X_out
);

    wire Load_IN;
    wire Encode_EN;
    wire ALU_EN;
    wire CRT_Start;
    wire MRC_Start;
    wire Out_EN;

    wire Encode_Done_all;
    wire ALU_Done_all;
    wire CRT_Done;
    wire MRC_Done;
    assign CRT_Done = 1'b0;

    wire [2:0] CU_state_dbg;

    reg [WIDTH_IN-1:0] A_reg, B_reg;
    reg [1:0]          OpSel_reg;

    always @(posedge clk) begin
        if (Load_IN) begin
            A_reg     <= A_in;
            B_reg     <= B_in;
            OpSel_reg <= Op_Sel;
        end
    end

    rns_cu u_cu (
        .clk         (clk),
        .rst_n       (rst_n),
        .Start       (Start),
        .Recon_Mode  (1'b1),
        .Done        (Done),
        .CU_state_dbg(CU_state_dbg),
        .Encode_Done (Encode_Done_all),
        .ALU_Done    (ALU_Done_all),
        .CRT_Done    (CRT_Done),
        .MRC_Done    (MRC_Done),
        .Load_IN     (Load_IN),
        .Encode_EN   (Encode_EN),
        .ALU_EN      (ALU_EN),
        .CRT_Start   (CRT_Start),
        .MRC_Start   (MRC_Start),
        .Out_EN      (Out_EN)
    );

    wire [W0-1:0] a_r0;
    wire [W1-1:0] a_r1;
    wire [W2-1:0] a_r2;
    wire [W3-1:0] a_r3;
    wire          Encode_Done_A;

    wire [W0-1:0] b_r0;
    wire [W1-1:0] b_r1;
    wire [W2-1:0] b_r2;
    wire [W3-1:0] b_r3;
    wire          Encode_Done_B;

    rns_encoder #(
        .WIDTH_IN (WIDTH_IN),
        .M0       (M0),
        .M1       (M1),
        .M2       (M2),
        .M3       (M3),
        .W0       (W0),
        .W1       (W1),
        .W2       (W2),
        .W3       (W3)
    ) u_enc_a (
        .clk         (clk),
        .rst_n       (rst_n),
        .Encode_EN   (Encode_EN),
        .x           (A_reg),
        .Encode_Done (Encode_Done_A),
        .r0          (a_r0),
        .r1          (a_r1),
        .r2          (a_r2),
        .r3          (a_r3)
    );

    rns_encoder #(
        .WIDTH_IN (WIDTH_IN),
        .M0       (M0),
        .M1       (M1),
        .M2       (M2),
        .M3       (M3),
        .W0       (W0),
        .W1       (W1),
        .W2       (W2),
        .W3       (W3)
    ) u_enc_b (
        .clk         (clk),
        .rst_n       (rst_n),
        .Encode_EN   (Encode_EN),
        .x           (B_reg),
        .Encode_Done (Encode_Done_B),
        .r0          (b_r0),
        .r1          (b_r1),
        .r2          (b_r2),
        .r3          (b_r3)
    );

    assign Encode_Done_all = Encode_Done_A & Encode_Done_B;

    wire [W0-1:0] z_r0;
    wire [W1-1:0] z_r1;
    wire [W2-1:0] z_r2;
    wire [W3-1:0] z_r3;

    wire slice0_done;
    wire slice1_done;
    wire slice2_done;
    wire slice3_done;

    rns_slice #(.MODULUS(M0), .WIDTH(W0)) u_slice0 (
        .clk(clk), .rst_n(rst_n), .ALU_EN(ALU_EN), .op_sel(OpSel_reg), .a(a_r0), .b(b_r0), .y(z_r0), .ALU_Done(slice0_done)
    );
    rns_slice #(.MODULUS(M1), .WIDTH(W1)) u_slice1 (
        .clk(clk), .rst_n(rst_n), .ALU_EN(ALU_EN), .op_sel(OpSel_reg), .a(a_r1), .b(b_r1), .y(z_r1), .ALU_Done(slice1_done)
    );
    rns_slice #(.MODULUS(M2), .WIDTH(W2)) u_slice2 (
        .clk(clk), .rst_n(rst_n), .ALU_EN(ALU_EN), .op_sel(OpSel_reg), .a(a_r2), .b(b_r2), .y(z_r2), .ALU_Done(slice2_done)
    );
    rns_slice #(.MODULUS(M3), .WIDTH(W3)) u_slice3 (
        .clk(clk), .rst_n(rst_n), .ALU_EN(ALU_EN), .op_sel(OpSel_reg), .a(a_r3), .b(b_r3), .y(z_r3), .ALU_Done(slice3_done)
    );

    assign ALU_Done_all = slice0_done & slice1_done & slice2_done & slice3_done;

    wire [WIDTH_IN-1:0] X_mrc;

    rns_mrc_recon #(
        .W0        (W0),
        .W1        (W1),
        .W2        (W2),
        .W3        (W3),
        .OUT_WIDTH (WIDTH_IN)
    ) u_mrc (
        .clk       (clk),
        .rst_n     (rst_n),
        .MRC_Start (MRC_Start),
        .r0        (z_r0),
        .r1        (z_r1),
        .r2        (z_r2),
        .r3        (z_r3),
        .X_out     (X_mrc),
        .MRC_Done  (MRC_Done)
    );

    reg [WIDTH_IN-1:0] X_reg;

    always @(posedge clk) begin
        if (Out_EN)
            X_reg <= X_mrc;
    end

    assign X_out = X_reg;

endmodule

designs/rns_mrc/tb/tb_rns_top_mrc.v
`timescale 1ns/1ps

module tb_rns_top_mrc;

    // Clock & Reset
    reg clk;
    reg rst_n;

    // DUT interface signals
    reg         Start;
    reg  [1:0]  Op_Sel;       // 00=ADD, 01=SUB, 10=MUL
    reg  [15:0] A_in;
    reg  [15:0] B_in;

    wire        Done;
    wire [15:0] X_out;

    // Instantiate MRC DUT
    rns_top_mrc #(
        .WIDTH_IN (16),
        .M0       (3),
        .M1       (5),
        .M2       (7),
        .M3       (11),
        .W0       (2),
        .W1       (3),
        .W2       (3),
        .W3       (4)
    ) dut (
        .clk   (clk),
        .rst_n (rst_n),
        .Start (Start),
        .Op_Sel(Op_Sel),
        .A_in  (A_in),
        .B_in  (B_in),
        .Done  (Done),
        .X_out (X_out)
    );

    // Clock generation: 100 MHz (10 ns period)
    initial begin
        clk = 1'b0;
        forever #5 clk = ~clk;
    end

    // VCD dump for workflow precheck / Surfer
    initial begin
        $dumpfile("rtl_precheck.vcd");
        $dumpvars(0, tb_rns_top_mrc);
    end

    // Task: run one ALU operation
    // op       : 00=ADD, 01=SUB, 10=MUL
    // a, b     : operands
    // expected : expected result mod 1155
    // name     : test name for printing
    task run_test;
        input [1:0]   op;
        input [15:0]  a;
        input [15:0]  b;
        input [15:0]  expected;
        input [127:0] name;
    begin
        Op_Sel = op;
        A_in   = a;
        B_in   = b;

        // Pulse Start for one clock cycle
        @(negedge clk);
        Start = 1'b1;
        @(negedge clk);
        Start = 1'b0;

        // Wait for completion
        @(posedge Done);
        #1;

        $display("[%0t] TEST %s | MRC | op=%b, A=%0d, B=%0d, X_out=%0d, expected=%0d",
                 $time, name, op, a, b, X_out, expected);

        if (X_out !== expected) begin
            $display("  -> FAIL");
        end else begin
            $display("  -> PASS");
        end

        @(negedge clk);
    end
    endtask

    // Reset and stimulus
    initial begin
        Start  = 1'b0;
        Op_Sel = 2'b00;
        A_in   = 16'd0;
        B_in   = 16'd0;

        rst_n = 1'b0;
        repeat (5) @(negedge clk);
        rst_n = 1'b1;
        @(negedge clk);

        // ADD
        run_test(2'b00, 16'd10,   16'd7,   16'd17,   "ADD_10_7");
        run_test(2'b00, 16'd1000, 16'd300, 16'd145,  "ADD_WRAP");

        // SUB
        run_test(2'b01, 16'd200,  16'd50,  16'd150,  "SUB_200_50");
        run_test(2'b01, 16'd50,   16'd200, 16'd1005, "SUB_WRAP");

        // MUL
        run_test(2'b10, 16'd11,   16'd17,  16'd187,  "MUL_11_17");
        run_test(2'b10, 16'd40,   16'd40,  16'd445,  "MUL_WRAP");

        $display("All MRC tests completed.");
        #20;
        $finish;
    end

endmodule

rns_mrc/latest/precheck/rtl/rtl_precheck.vcd
$date
	Thu May  7 09:49:20 2026
$end
$version
	Icarus Verilog
$end
$timescale
	1ps
$end
$scope module tb_rns_top_mrc $end
$var wire 16 ! X_out [15:0] $end
$var wire 1 " Done $end
$var reg 16 # A_in [15:0] $end
$var reg 16 $ B_in [15:0] $end
$var reg 2 % Op_Sel [1:0] $end
$var reg 1 & Start $end
$var reg 1 ' clk $end
$var reg 1 ( rst_n $end
$scope module dut $end
$var wire 1 ) ALU_Done_all $end
$var wire 16 * A_in [15:0] $end
$var wire 16 + B_in [15:0] $end
$var wire 1 , CRT_Done $end
$var wire 1 - Encode_Done_all $end
$var wire 2 . Op_Sel [1:0] $end
$var wire 1 & Start $end
$var wire 16 / X_out [15:0] $end
$var wire 1 ' clk $end
$var wire 1 ( rst_n $end
$var wire 4 0 z_r3 [3:0] $end
$var wire 3 1 z_r2 [2:0] $end
$var wire 3 2 z_r1 [2:0] $end
$var wire 2 3 z_r0 [1:0] $end
$var wire 1 4 slice3_done $end
$var wire 1 5 slice2_done $end
$var wire 1 6 slice1_done $end
$var wire 1 7 slice0_done $end
$var wire 4 8 b_r3 [3:0] $end
$var wire 3 9 b_r2 [2:0] $end
$var wire 3 : b_r1 [2:0] $end
$var wire 2 ; b_r0 [1:0] $end
$var wire 4 < a_r3 [3:0] $end
$var wire 3 = a_r2 [2:0] $end
$var wire 3 > a_r1 [2:0] $end
$var wire 2 ? a_r0 [1:0] $end
$var wire 16 @ X_mrc [15:0] $end
$var wire 1 A Out_EN $end
$var wire 1 B MRC_Start $end
$var wire 1 C MRC_Done $end
$var wire 1 D Load_IN $end
$var wire 1 E Encode_EN $end
$var wire 1 F Encode_Done_B $end
$var wire 1 G Encode_Done_A $end
$var wire 1 " Done $end
$var wire 3 H CU_state_dbg [2:0] $end
$var wire 1 I CRT_Start $end
$var wire 1 J ALU_EN $end
$var parameter 32 K M0 $end
$var parameter 32 L M1 $end
$var parameter 32 M M2 $end
$var parameter 32 N M3 $end
$var parameter 32 O W0 $end
$var parameter 32 P W1 $end
$var parameter 32 Q W2 $end
$var parameter 32 R W3 $end
$var parameter 32 S WIDTH_IN $end
$var reg 16 T A_reg [15:0] $end
$var reg 16 U B_reg [15:0] $end
$var reg 2 V OpSel_reg [1:0] $end
$var reg 16 W X_reg [15:0] $end
$scope module u_cu $end
$var wire 1 ) ALU_Done $end
$var wire 1 , CRT_Done $end
$var wire 3 X CU_state_dbg [2:0] $end
$var wire 1 - Encode_Done $end
$var wire 1 Y Recon_Mode $end
$var wire 1 & Start $end
$var wire 1 ' clk $end
$var wire 1 ( rst_n $end
$var wire 1 Z recon_done_sel $end
$var wire 1 C MRC_Done $end
$var parameter 3 [ S_ALU $end
$var parameter 3 \ S_DONE $end
$var parameter 3 ] S_ENCODE $end
$var parameter 3 ^ S_IDLE $end
$var parameter 3 _ S_LOAD $end
$var parameter 3 ` S_OUT $end
$var parameter 3 a S_RECON $end
$var reg 1 J ALU_EN $end
$var reg 1 I CRT_Start $end
$var reg 1 " Done $end
$var reg 1 E Encode_EN $end
$var reg 1 D Load_IN $end
$var reg 1 B MRC_Start $end
$var reg 1 A Out_EN $end
$var reg 3 b next_state [2:0] $end
$var reg 3 c state [2:0] $end
$upscope $end
$scope module u_enc_a $end
$var wire 1 E Encode_EN $end
$var wire 1 ' clk $end
$var wire 1 ( rst_n $end
$var wire 16 d x [15:0] $end
$var wire 4 e r3_next [3:0] $end
$var wire 3 f r2_next [2:0] $end
$var wire 3 g r1_next [2:0] $end
$var wire 2 h r0_next [1:0] $end
$var parameter 32 i M0 $end
$var parameter 32 j M1 $end
$var parameter 32 k M2 $end
$var parameter 32 l M3 $end
$var parameter 32 m W0 $end
$var parameter 32 n W1 $end
$var parameter 32 o W2 $end
$var parameter 32 p W3 $end
$var parameter 32 q WIDTH_IN $end
$var reg 1 G Encode_Done $end
$var reg 2 r r0 [1:0] $end
$var reg 3 s r1 [2:0] $end
$var reg 3 t r2 [2:0] $end
$var reg 4 u r3 [3:0] $end
$upscope $end
$scope module u_enc_b $end
$var wire 1 E Encode_EN $end
$var wire 1 ' clk $end
$var wire 1 ( rst_n $end
$var wire 16 v x [15:0] $end
$var wire 4 w r3_next [3:0] $end
$var wire 3 x r2_next [2:0] $end
$var wire 3 y r1_next [2:0] $end
$var wire 2 z r0_next [1:0] $end
$var parameter 32 { M0 $end
$var parameter 32 | M1 $end
$var parameter 32 } M2 $end
$var parameter 32 ~ M3 $end
$var parameter 32 !" W0 $end
$var parameter 32 "" W1 $end
$var parameter 32 #" W2 $end
$var parameter 32 $" W3 $end
$var parameter 32 %" WIDTH_IN $end
$var reg 1 F Encode_Done $end
$var reg 2 &" r0 [1:0] $end
$var reg 3 '" r1 [2:0] $end
$var reg 3 (" r2 [2:0] $end
$var reg 4 )" r3 [3:0] $end
$upscope $end
$scope module u_mrc $end
$var wire 1 B MRC_Start $end
$var wire 1 ' clk $end
$var wire 1 ( rst_n $end
$var wire 1 *" start_pulse $end
$var wire 11 +" total_mod_w [10:0] $end
$var wire 4 ," t4_w [3:0] $end
$var wire 3 -" t3_w [2:0] $end
$var wire 3 ." t2_w [2:0] $end
$var wire 4 /" r3 [3:0] $end
$var wire 3 0" r2 [2:0] $end
$var wire 3 1" r1 [2:0] $end
$var wire 2 2" r0 [1:0] $end
$var wire 11 3" X4_w [10:0] $end
$var wire 7 4" X3_next_w [6:0] $end
$var wire 4 5" X2_next_w [3:0] $end
$var parameter 32 6" INV_12 $end
$var parameter 32 7" INV_123 $end
$var parameter 32 8" INV_1234 $end
$var parameter 32 9" MOD0 $end
$var parameter 32 :" MOD1 $end
$var parameter 32 ;" MOD2 $end
$var parameter 32 <" MOD3 $end
$var parameter 32 =" MPREV1 $end
$var parameter 32 >" MPREV2 $end
$var parameter 32 ?" MPREV3 $end
$var parameter 32 @" M_TOTAL $end
$var parameter 32 A" OUT_WIDTH $end
$var parameter 3 B" S_DONE $end
$var parameter 3 C" S_IDLE $end
$var parameter 3 D" S_S1 $end
$var parameter 3 E" S_S2 $end
$var parameter 3 F" S_S3 $end
$var parameter 3 G" S_S4 $end
$var parameter 32 H" W0 $end
$var parameter 32 I" W1 $end
$var parameter 32 J" W2 $end
$var parameter 32 K" W3 $end
$var reg 1 C MRC_Done $end
$var reg 2 L" X1_r [1:0] $end
$var reg 4 M" X2_r [3:0] $end
$var reg 7 N" X3_r [6:0] $end
$var reg 16 O" X_out [15:0] $end
$var reg 2 P" r0_mod_r [1:0] $end
$var reg 3 Q" r1_mod_r [2:0] $end
$var reg 3 R" r2_mod_r [2:0] $end
$var reg 4 S" r3_mod_r [3:0] $end
$var reg 1 T" start_d $end
$var reg 3 U" state [2:0] $end
$scope function norm_mod $end
$var integer 32 V" m [31:0] $end
$var integer 32 W" t [31:0] $end
$var integer 32 X" x [31:0] $end
$upscope $end
$upscope $end
$scope module u_slice0 $end
$var wire 1 J ALU_EN $end
$var wire 2 Y" a [1:0] $end
$var wire 2 Z" b [1:0] $end
$var wire 1 ' clk $end
$var wire 2 [" op_sel [1:0] $end
$var wire 1 ( rst_n $end
$var parameter 32 \" MODULUS $end
$var parameter 32 ]" WIDTH $end
$var reg 1 7 ALU_Done $end
$var reg 1 ^" start_d $end
$var reg 2 _" y [1:0] $end
$var reg 2 `" y_next [1:0] $end
$var integer 32 a" tmp [31:0] $end
$upscope $end
$scope module u_slice1 $end
$var wire 1 J ALU_EN $end
$var wire 3 b" a [2:0] $end
$var wire 3 c" b [2:0] $end
$var wire 1 ' clk $end
$var wire 2 d" op_sel [1:0] $end
$var wire 1 ( rst_n $end
$var parameter 32 e" MODULUS $end
$var parameter 32 f" WIDTH $end
$var reg 1 6 ALU_Done $end
$var reg 1 g" start_d $end
$var reg 3 h" y [2:0] $end
$var reg 3 i" y_next [2:0] $end
$var integer 32 j" tmp [31:0] $end
$upscope $end
$scope module u_slice2 $end
$var wire 1 J ALU_EN $end
$var wire 3 k" a [2:0] $end
$var wire 3 l" b [2:0] $end
$var wire 1 ' clk $end
$var wire 2 m" op_sel [1:0] $end
$var wire 1 ( rst_n $end
$var parameter 32 n" MODULUS $end
$var parameter 32 o" WIDTH $end
$var reg 1 5 ALU_Done $end
$var reg 1 p" start_d $end
$var reg 3 q" y [2:0] $end
$var reg 3 r" y_next [2:0] $end
$var integer 32 s" tmp [31:0] $end
$upscope $end
$scope module u_slice3 $end
$var wire 1 J ALU_EN $end
$var wire 4 t" a [3:0] $end
$var wire 4 u" b [3:0] $end
$var wire 1 ' clk $end
$var wire 2 v" op_sel [1:0] $end
$var wire 1 ( rst_n $end
$var parameter 32 w" MODULUS $end
$var parameter 32 x" WIDTH $end
$var reg 1 4 ALU_Done $end
$var reg 1 y" start_d $end
$var reg 4 z" y [3:0] $end
$var reg 4 {" y_next [3:0] $end
$var integer 32 |" tmp [31:0] $end
$upscope $end
$upscope $end
$scope task run_test $end
$var reg 16 }" a [15:0] $end
$var reg 16 ~" b [15:0] $end
$var reg 16 !# expected [15:0] $end
$var reg 128 "# name [127:0] $end
$var reg 2 ## op [1:0] $end
$upscope $end
$upscope $end
$enddefinitions $end
$comment Show the parameter values. $end
$dumpall
b100 x"
b1011 w"
b11 o"
b111 n"
b11 f"
b101 e"
b10 ]"
b11 \"
b100 K"
b11 J"
b11 I"
b10 H"
b100 G"
b11 F"
b10 E"
b1 D"
b0 C"
b101 B"
b10000 A"
b10010000011 @"
b1101001 ?"
b1111 >"
b11 ="
b1011 <"
b111 ;"
b101 :"
b11 9"
b10 8"
b1 7"
b10 6"
b10000 %"
b100 $"
b11 #"
b11 ""
b10 !"
b1011 ~
b111 }
b101 |
b11 {
b10000 q
b100 p
b11 o
b11 n
b10 m
b1011 l
b111 k
b101 j
b11 i
b100 a
b101 `
b1 _
b0 ^
b10 ]
b110 \
b11 [
b10000 S
b100 R
b11 Q
b11 P
b10 O
b1011 N
b111 M
b101 L
b11 K
$end
#0
$dumpvars
bx ##
bx "#
bx !#
bx ~"
bx }"
bx |"
bx {"
bx z"
xy"
bx v"
bx u"
bx t"
bx s"
bx r"
bx q"
xp"
bx m"
bx l"
bx k"
bx j"
bx i"
bx h"
xg"
bx d"
bx c"
bx b"
bx a"
bx `"
bx _"
x^"
bx ["
bx Z"
bx Y"
bx X"
bx W"
b111 V"
bx U"
xT"
bx S"
bx R"
bx Q"
bx P"
bx O"
bx N"
bx M"
bx L"
bx 5"
bx 4"
bx 3"
bx 2"
bx 1"
bx 0"
bx /"
bx ."
bx -"
bx ,"
bx +"
0*"
bx )"
bx ("
bx '"
bx &"
bx z
bx y
bx x
bx w
bx v
bx u
bx t
bx s
bx r
bx h
bx g
bx f
bx e
bx d
bx c
b0 b
xZ
1Y
bx X
bx W
bx V
bx U
bx T
0J
0I
bx H
xG
xF
0E
0D
xC
0B
0A
bx @
bx ?
bx >
bx =
bx <
bx ;
bx :
bx 9
bx 8
x7
x6
x5
x4
bx 3
bx 2
bx 1
bx 0
bx /
b0 .
x-
0,
b0 +
b0 *
x)
0(
0'
0&
b0 %
b0 $
b0 #
0"
bx !
$end
#5000
0-
0)
0Z
b0 H
b0 X
b0 c
0G
0F
07
0^"
06
0g"
05
0p"
04
0y"
0C
0T"
b0 U"
1'
#10000
0'
#15000
1'
#20000
0'
#25000
1'
#30000
0'
#35000
1'
#40000
0'
#45000
1'
#50000
1(
0'
#55000
1'
#60000
b111 $
b111 +
b1010 #
b1010 *
b100000101000100010001000101111100110001001100000101111100110111 "#
b10001 !#
b111 ~"
b1010 }"
b0 ##
0'
#65000
1'
#70000
b1 b
1&
0'
#75000
1D
b10 b
b1 H
b1 X
b1 c
1'
#80000
b10 b
0&
0'
#85000
1E
0D
bx a"
bx `"
bx j"
bx i"
bx s"
bx r"
bx |"
bx {"
b1 z
b10 y
b0 x
b111 w
b1 h
b0 g
b11 f
b1010 e
b10 H
b10 X
b10 c
b0 V
b0 ["
b0 d"
b0 m"
b0 v"
b111 U
b111 v
b1010 T
b1010 d
1'
#90000
0'
