designs/rns_crt/src/rns_crt_recon.v
`timescale 1ns/1ps

module rns_crt_recon #(
    parameter W0        = 2,
    parameter W1        = 3,
    parameter W2        = 3,
    parameter W3        = 4,
    parameter OUT_WIDTH = 16
)(
    input  wire                 clk,
    input  wire                 rst_n,
    input  wire                 CRT_Start,
    input  wire [W0-1:0]        r0,
    input  wire [W1-1:0]        r1,
    input  wire [W2-1:0]        r2,
    input  wire [W3-1:0]        r3,
    output reg  [OUT_WIDTH-1:0] X_out,
    output reg                  CRT_Done
);

    localparam integer M    = 1155;

    localparam integer M0   = 385;
    localparam integer M1   = 231;
    localparam integer M2   = 165;
    localparam integer M3   = 105;

    localparam integer INV0 = 1;
    localparam integer INV1 = 1;
    localparam integer INV2 = 2;
    localparam integer INV3 = 2;

    reg [1:0]  x0_mod;
    reg [2:0]  x1_mod;
    reg [2:0]  x2_mod;
    reg [3:0]  x3_mod;

    reg [9:0]  term0;
    reg [9:0]  term1;
    reg [10:0] term2;
    reg [11:0] term3;
    reg [12:0] total;
    reg [10:0] total_mod;

    reg [OUT_WIDTH-1:0] X_next;
    reg start_d;

    function integer norm_mod;
        input integer x;
        input integer m;
        integer t;
        begin
            t = x % m;
            if (t < 0)
                t = t + m;
            norm_mod = t;
        end
    endfunction

    always @* begin
        x0_mod    = norm_mod(r0, 3);
        x1_mod    = norm_mod(r1, 5);
        x2_mod    = norm_mod(r2, 7);
        x3_mod    = norm_mod(r3, 11);

        term0     = x0_mod * M0 * INV0;
        term1     = x1_mod * M1 * INV1;
        term2     = x2_mod * M2 * INV2;
        term3     = x3_mod * M3 * INV3;

        total     = term0 + term1 + term2 + term3;
        total_mod = norm_mod(total, M);

        X_next    = total_mod;
    end

    always @(posedge clk) begin
        if (!rst_n) begin
            CRT_Done <= 1'b0;
            start_d  <= 1'b0;
        end else begin
            CRT_Done <= start_d;
            start_d  <= CRT_Start;

            if (CRT_Start)
                X_out <= X_next;
        end
    end

endmodule

designs/rns_mrc/src/rns_slice.v
`timescale 1ns/1ps

// Function: Per-Modulus RNS ALU Slice (ADD / SUB / MUL)
// Hardware counterpart of Python per-channel ops in ops.py:
//   add(a, b, m) = (a + b) % m
//   sub(a, b, m) = (a - b) % m
//   mul(a, b, m) = (a * b) % m

// Data Path: Stage 3 – Modular ALUs
// Control:
//   - CU asserts ALU_EN (start operation for the specific slice)
//   - Slice asserts ALU_Done HIGH exactly one cycle later (Handshake)

// Operation Select (op_sel):
//   2'b00 : ADD
//   2'b01 : SUB
//   2'b10 : MUL
//   others: result = 0

module rns_slice #(
    parameter MODULUS = 3,
    parameter WIDTH   = 2
)(
    input  wire                 clk,
    input  wire                 rst_n,
    input  wire                 ALU_EN,
    input  wire [1:0]           op_sel,
    input  wire [WIDTH-1:0]     a,
    input  wire [WIDTH-1:0]     b,
    output reg  [WIDTH-1:0]     y,
    output reg                  ALU_Done
);

    reg [WIDTH-1:0] y_next;
    reg             start_d;
    integer         tmp;

    always @* begin
        y_next = {WIDTH{1'b0}};
        tmp    = 0;

        case (op_sel)
            2'b00: begin
                tmp    = a + b;
                tmp    = tmp % MODULUS;
                y_next = tmp[WIDTH-1:0];
            end

            2'b01: begin
                tmp    = a + MODULUS - b;
                tmp    = tmp % MODULUS;
                y_next = tmp[WIDTH-1:0];
            end

            2'b10: begin
                tmp    = a * b;
                tmp    = tmp % MODULUS;
                y_next = tmp[WIDTH-1:0];
            end

            default: begin
                y_next = {WIDTH{1'b0}};
            end
        endcase
    end

    always @(posedge clk) begin
        if (!rst_n) begin
            start_d  <= 1'b0;
            ALU_Done <= 1'b0;
        end else begin
            ALU_Done <= start_d;
            start_d  <= ALU_EN;

            if (ALU_EN)
                y <= y_next;
        end
    end

endmodule

designs/rns_crt/src/rns_encoder.v
`timescale 1ns/1ps

// Function: Forward Conversion (Binary → Residues)
// Hardware counterpart of Python encode(): encode(x, [3, 5, 7, 11])

// Data Path: Stage 2 – Encoder Bank
// Control:
//   - CU asserts Encode_EN
//   - Encoder outputs Encode_Done high for 1 cycle
// Moduli Set: M0 = 3, M1 = 5, M2 = 7, M3 = 11

// Notes:
//   - Unsigned domain only (x ≥ 0).
//   - One-cycle latency.
//   - Modulus operations are constant-mod (synthesizable)
//   - Reset is kept on handshake only; residue outputs are not reset

module rns_encoder #(
    parameter WIDTH_IN = 16,
    parameter M0 = 3,
    parameter M1 = 5,
    parameter M2 = 7,
    parameter M3 = 11,
    parameter W0 = 2,
    parameter W1 = 3,
    parameter W2 = 3,
    parameter W3 = 4
)(
    input  wire                 clk,
    input  wire                 rst_n,
    input  wire                 Encode_EN,
    input  wire [WIDTH_IN-1:0]  x,
    output reg                  Encode_Done,
    output reg [W0-1:0]         r0,
    output reg [W1-1:0]         r1,
    output reg [W2-1:0]         r2,
    output reg [W3-1:0]         r3
);

    wire [W0-1:0] r0_next;
    wire [W1-1:0] r1_next;
    wire [W2-1:0] r2_next;
    wire [W3-1:0] r3_next;

    assign r0_next = x % M0;
    assign r1_next = x % M1;
    assign r2_next = x % M2;
    assign r3_next = x % M3;

    always @(posedge clk) begin
        if (!rst_n) begin
            Encode_Done <= 1'b0;
        end else begin
            Encode_Done <= 1'b0;

            if (Encode_EN) begin
                r0 <= r0_next;
                r1 <= r1_next;
                r2 <= r2_next;
                r3 <= r3_next;
                Encode_Done <= 1'b1;
            end
        end
    end

endmodule

designs/rns_crt/src/rns_cu.v
// Function: Control Unit for RNS ALU (CU FSM)

// Controls the pipeline: 
//   IDLE -> LOAD -> ENCODE -> ALU -> RECON -> OUT -> DONE

// Controls:
//   - rns_encoder.v   (Encode_EN / Encode_Done)
//   - rns_slice.v     (ALU_EN / ALU_Done)
//   - rns_crt_recon.v (CRT_Start / CRT_Done)
//   - rns_mrc_recon.v (MRC_Start / MRC_Done)

// Reconstruction Selection (runtime):
//   Recon_Mode = 0 -> use CRT
//   Recon_Mode = 1 -> use MRC

`timescale 1ns/1ps

module rns_cu (
    // Clock & Reset
    input  wire clk,
    input  wire rst_n,

    // External control
    input  wire Start,         // Start a new operation
    input  wire Recon_Mode,    // 0 = CRT, 1 = MRC
    output reg  Done,          // High when full operation completed
    output wire [2:0] CU_state_dbg, // Debug: Current CU FSM state

    // Handshakes from Data Path
    input  wire Encode_Done,   // Encoders finished
    input  wire ALU_Done,      // All ALU slices finished
    input  wire CRT_Done,      // CRT reconstructor finished
    input  wire MRC_Done,      // MRC reconstructor finished

    // Control outputs to Data Path 
    output reg  Load_IN,       // Latch A, B, OpSel into input regs
    output reg  Encode_EN,     // Enable encoders
    output reg  ALU_EN,        // Enable modular ALUs
    output reg  CRT_Start,     // Trigger CRT reconstruction
    output reg  MRC_Start,     // Trigger MRC reconstruction
    output reg  Out_EN         // Latch final X_out register
);

    // State Encoding
    localparam [2:0]
        S_IDLE   = 3'd0,
        S_LOAD   = 3'd1,
        S_ENCODE = 3'd2,
        S_ALU    = 3'd3,
        S_RECON  = 3'd4,
        S_OUT    = 3'd5,
        S_DONE   = 3'd6;

    reg [2:0] state, next_state;

    // State Register
    always @(posedge clk) begin
        if (!rst_n)
            state <= S_IDLE;
        else
            state <= next_state;
    end

    // Next-State Logic
    wire recon_done_sel;
    assign recon_done_sel = (Recon_Mode == 1'b0) ? CRT_Done : MRC_Done;

    always @* begin
        next_state = state; // Default hold

        case (state)
            S_IDLE:   if (Start)       next_state = S_LOAD;
            S_LOAD:                    next_state = S_ENCODE;
            S_ENCODE: if (Encode_Done) next_state = S_ALU;
            S_ALU:    if (ALU_Done)    next_state = S_RECON;
            S_RECON:  if (recon_done_sel) next_state = S_OUT;
            S_OUT:                     next_state = S_DONE;
            S_DONE:   if (!Start)      next_state = S_IDLE;
            default:                   next_state = S_IDLE;
        endcase
    end

    // Output Logic (Moore FSM)
    always @* begin
        // Default all controls LOW
        Load_IN   = 1'b0;
        Encode_EN = 1'b0;
        ALU_EN    = 1'b0;
        CRT_Start = 1'b0;
        MRC_Start = 1'b0;
        Out_EN    = 1'b0;
        Done      = 1'b0;

        case (state)
            S_LOAD:   Load_IN   = 1'b1;
            S_ENCODE: Encode_EN = 1'b1;
            S_ALU:    ALU_EN    = 1'b1;

            S_RECON: begin
                if (Recon_Mode == 1'b0)
                    CRT_Start = 1'b1;
                else
                    MRC_Start = 1'b1;
            end

            S_OUT:  Out_EN = 1'b1;
            S_DONE: Done   = 1'b1;
        endcase
    end

    // Expose internal state for debugging
    assign CU_state_dbg = state;

endmodule

designs/rns_crt/src/rns_top_crt.v
`timescale 1ns/1ps

// CRT-only Top-Level RNS ALU
// Structurally aligned to CRNS wrapper style:
// - direct Load_IN capture
// - no datapath async reset
// - unused MRC_Done tied low

module rns_top_crt #(
    parameter WIDTH_IN  = 16,
    parameter M0 = 3,
    parameter M1 = 5,
    parameter M2 = 7,
    parameter M3 = 11,
    parameter W0 = 2,
    parameter W1 = 3,
    parameter W2 = 3,
    parameter W3 = 4
)(
    input  wire                 clk,
    input  wire                 rst_n,
    input  wire                 Start,
    input  wire [1:0]           Op_Sel,
    input  wire [WIDTH_IN-1:0]  A_in,
    input  wire [WIDTH_IN-1:0]  B_in,
    output wire                 Done,
    output wire [WIDTH_IN-1:0]  X_out
);

    wire Load_IN;
    wire Encode_EN;
    wire ALU_EN;
    wire CRT_Start;
    wire MRC_Start;
    wire Out_EN;

    wire Encode_Done_all;
    wire ALU_Done_all;
    wire CRT_Done;
    wire MRC_Done;
    assign MRC_Done = 1'b0;

    wire [2:0] CU_state_dbg;

    reg [WIDTH_IN-1:0] A_reg, B_reg;
    reg [1:0]          OpSel_reg;

    always @(posedge clk) begin
        if (Load_IN) begin
            A_reg     <= A_in;
            B_reg     <= B_in;
            OpSel_reg <= Op_Sel;
        end
    end

    rns_cu u_cu (
        .clk         (clk),
        .rst_n       (rst_n),
        .Start       (Start),
        .Recon_Mode  (1'b0),
        .Done        (Done),
        .CU_state_dbg(CU_state_dbg),
        .Encode_Done (Encode_Done_all),
        .ALU_Done    (ALU_Done_all),
        .CRT_Done    (CRT_Done),
        .MRC_Done    (MRC_Done),
        .Load_IN     (Load_IN),
        .Encode_EN   (Encode_EN),
        .ALU_EN      (ALU_EN),
        .CRT_Start   (CRT_Start),
        .MRC_Start   (MRC_Start),
        .Out_EN      (Out_EN)
    );

    wire [W0-1:0] a_r0;
    wire [W1-1:0] a_r1;
    wire [W2-1:0] a_r2;
    wire [W3-1:0] a_r3;
    wire          Encode_Done_A;

    wire [W0-1:0] b_r0;
    wire [W1-1:0] b_r1;
    wire [W2-1:0] b_r2;
    wire [W3-1:0] b_r3;
    wire          Encode_Done_B;

    rns_encoder #(
        .WIDTH_IN (WIDTH_IN),
        .M0       (M0),
        .M1       (M1),
        .M2       (M2),
        .M3       (M3),
        .W0       (W0),
        .W1       (W1),
        .W2       (W2),
        .W3       (W3)
    ) u_enc_a (
        .clk         (clk),
        .rst_n       (rst_n),
        .Encode_EN   (Encode_EN),
        .x           (A_reg),
        .Encode_Done (Encode_Done_A),
        .r0          (a_r0),
        .r1          (a_r1),
        .r2          (a_r2),
        .r3          (a_r3)
    );

    rns_encoder #(
        .WIDTH_IN (WIDTH_IN),
        .M0       (M0),
        .M1       (M1),
        .M2       (M2),
        .M3       (M3),
        .W0       (W0),
        .W1       (W1),
        .W2       (W2),
        .W3       (W3)
    ) u_enc_b (
        .clk         (clk),
        .rst_n       (rst_n),
        .Encode_EN   (Encode_EN),
        .x           (B_reg),
        .Encode_Done (Encode_Done_B),
        .r0          (b_r0),
        .r1          (b_r1),
        .r2          (b_r2),
        .r3          (b_r3)
    );

    assign Encode_Done_all = Encode_Done_A & Encode_Done_B;

    wire [W0-1:0] z_r0;
    wire [W1-1:0] z_r1;
    wire [W2-1:0] z_r2;
    wire [W3-1:0] z_r3;

    wire slice0_done;
    wire slice1_done;
    wire slice2_done;
    wire slice3_done;

    rns_slice #(.MODULUS(M0), .WIDTH(W0)) u_slice0 (
        .clk(clk), .rst_n(rst_n), .ALU_EN(ALU_EN), .op_sel(OpSel_reg), .a(a_r0), .b(b_r0), .y(z_r0), .ALU_Done(slice0_done)
    );
    rns_slice #(.MODULUS(M1), .WIDTH(W1)) u_slice1 (
        .clk(clk), .rst_n(rst_n), .ALU_EN(ALU_EN), .op_sel(OpSel_reg), .a(a_r1), .b(b_r1), .y(z_r1), .ALU_Done(slice1_done)
    );
    rns_slice #(.MODULUS(M2), .WIDTH(W2)) u_slice2 (
        .clk(clk), .rst_n(rst_n), .ALU_EN(ALU_EN), .op_sel(OpSel_reg), .a(a_r2), .b(b_r2), .y(z_r2), .ALU_Done(slice2_done)
    );
    rns_slice #(.MODULUS(M3), .WIDTH(W3)) u_slice3 (
        .clk(clk), .rst_n(rst_n), .ALU_EN(ALU_EN), .op_sel(OpSel_reg), .a(a_r3), .b(b_r3), .y(z_r3), .ALU_Done(slice3_done)
    );

    assign ALU_Done_all = slice0_done & slice1_done & slice2_done & slice3_done;

    wire [WIDTH_IN-1:0] X_crt;

    rns_crt_recon #(
        .W0        (W0),
        .W1        (W1),
        .W2        (W2),
        .W3        (W3),
        .OUT_WIDTH (WIDTH_IN)
    ) u_crt (
        .clk       (clk),
        .rst_n     (rst_n),
        .CRT_Start (CRT_Start),
        .r0        (z_r0),
        .r1        (z_r1),
        .r2        (z_r2),
        .r3        (z_r3),
        .X_out     (X_crt),
        .CRT_Done  (CRT_Done)
    );

    reg [WIDTH_IN-1:0] X_reg;

    always @(posedge clk) begin
        if (Out_EN)
            X_reg <= X_crt;
    end

    assign X_out = X_reg;

endmodule

designs/rns_crt/tb/tb_rns_top_crt.v
`timescale 1ns/1ps

module tb_rns_top_crt;

    // Clock & Reset
    reg clk;
    reg rst_n;

    // DUT interface signals
    reg         Start;
    reg  [1:0]  Op_Sel;       // 00=ADD, 01=SUB, 10=MUL
    reg  [15:0] A_in;
    reg  [15:0] B_in;

    wire        Done;
    wire [15:0] X_out;

    // Instantiate CRT DUT
    rns_top_crt #(
        .WIDTH_IN (16),
        .M0       (3),
        .M1       (5),
        .M2       (7),
        .M3       (11),
        .W0       (2),
        .W1       (3),
        .W2       (3),
        .W3       (4)
    ) dut (
        .clk   (clk),
        .rst_n (rst_n),
        .Start (Start),
        .Op_Sel(Op_Sel),
        .A_in  (A_in),
        .B_in  (B_in),
        .Done  (Done),
        .X_out (X_out)
    );

    // Clock generation: 100 MHz (10 ns period)
    initial begin
        clk = 1'b0;
        forever #5 clk = ~clk;
    end

    // VCD dump for workflow precheck / Surfer
    initial begin
        $dumpfile("rtl_precheck.vcd");
        $dumpvars(0, tb_rns_top_crt);
    end

    // Task: run one ALU operation
    // op       : 00=ADD, 01=SUB, 10=MUL
    // a, b     : operands
    // expected : expected result mod 1155
    // name     : test name for printing
    task run_test;
        input [1:0]   op;
        input [15:0]  a;
        input [15:0]  b;
        input [15:0]  expected;
        input [127:0] name;
    begin
        Op_Sel = op;
        A_in   = a;
        B_in   = b;

        // Pulse Start for one clock cycle
        @(negedge clk);
        Start = 1'b1;
        @(negedge clk);
        Start = 1'b0;

        // Wait for completion
        @(posedge Done);
        #1;

        $display("[%0t] TEST %s | CRT | op=%b, A=%0d, B=%0d, X_out=%0d, expected=%0d",
                 $time, name, op, a, b, X_out, expected);

        if (X_out !== expected) begin
            $display("  -> FAIL");
        end else begin
            $display("  -> PASS");
        end

        @(negedge clk);
    end
    endtask

    // Reset and stimulus
    initial begin
        Start  = 1'b0;
        Op_Sel = 2'b00;
        A_in   = 16'd0;
        B_in   = 16'd0;

        rst_n = 1'b0;
        repeat (5) @(negedge clk);
        rst_n = 1'b1;
        @(negedge clk);

        // ADD
        run_test(2'b00, 16'd10,   16'd7,   16'd17,   "ADD_10_7");
        run_test(2'b00, 16'd1000, 16'd300, 16'd145,  "ADD_WRAP");

        // SUB
        run_test(2'b01, 16'd200,  16'd50,  16'd150,  "SUB_200_50");
        run_test(2'b01, 16'd50,   16'd200, 16'd1005, "SUB_WRAP");

        // MUL
        run_test(2'b10, 16'd11,   16'd17,  16'd187,  "MUL_11_17");
        run_test(2'b10, 16'd40,   16'd40,  16'd445,  "MUL_WRAP");

        $display("All CRT tests completed.");
        #20;
        $finish;
    end

endmodule

rns_crt/latest/precheck/rtl/rtl_precheck.vcd
$date
	Thu May  7 09:49:11 2026
$end
$version
	Icarus Verilog
$end
$timescale
	1ps
$end
$scope module tb_rns_top_crt $end
$var wire 16 ! X_out [15:0] $end
$var wire 1 " Done $end
$var reg 16 # A_in [15:0] $end
$var reg 16 $ B_in [15:0] $end
$var reg 2 % Op_Sel [1:0] $end
$var reg 1 & Start $end
$var reg 1 ' clk $end
$var reg 1 ( rst_n $end
$scope module dut $end
$var wire 1 ) ALU_Done_all $end
$var wire 16 * A_in [15:0] $end
$var wire 16 + B_in [15:0] $end
$var wire 1 , Encode_Done_all $end
$var wire 1 - MRC_Done $end
$var wire 2 . Op_Sel [1:0] $end
$var wire 1 & Start $end
$var wire 16 / X_out [15:0] $end
$var wire 1 ' clk $end
$var wire 1 ( rst_n $end
$var wire 4 0 z_r3 [3:0] $end
$var wire 3 1 z_r2 [2:0] $end
$var wire 3 2 z_r1 [2:0] $end
$var wire 2 3 z_r0 [1:0] $end
$var wire 1 4 slice3_done $end
$var wire 1 5 slice2_done $end
$var wire 1 6 slice1_done $end
$var wire 1 7 slice0_done $end
$var wire 4 8 b_r3 [3:0] $end
$var wire 3 9 b_r2 [2:0] $end
$var wire 3 : b_r1 [2:0] $end
$var wire 2 ; b_r0 [1:0] $end
$var wire 4 < a_r3 [3:0] $end
$var wire 3 = a_r2 [2:0] $end
$var wire 3 > a_r1 [2:0] $end
$var wire 2 ? a_r0 [1:0] $end
$var wire 16 @ X_crt [15:0] $end
$var wire 1 A Out_EN $end
$var wire 1 B MRC_Start $end
$var wire 1 C Load_IN $end
$var wire 1 D Encode_EN $end
$var wire 1 E Encode_Done_B $end
$var wire 1 F Encode_Done_A $end
$var wire 1 " Done $end
$var wire 3 G CU_state_dbg [2:0] $end
$var wire 1 H CRT_Start $end
$var wire 1 I CRT_Done $end
$var wire 1 J ALU_EN $end
$var parameter 32 K M0 $end
$var parameter 32 L M1 $end
$var parameter 32 M M2 $end
$var parameter 32 N M3 $end
$var parameter 32 O W0 $end
$var parameter 32 P W1 $end
$var parameter 32 Q W2 $end
$var parameter 32 R W3 $end
$var parameter 32 S WIDTH_IN $end
$var reg 16 T A_reg [15:0] $end
$var reg 16 U B_reg [15:0] $end
$var reg 2 V OpSel_reg [1:0] $end
$var reg 16 W X_reg [15:0] $end
$scope module u_crt $end
$var wire 1 ' clk $end
$var wire 1 ( rst_n $end
$var wire 4 X r3 [3:0] $end
$var wire 3 Y r2 [2:0] $end
$var wire 3 Z r1 [2:0] $end
$var wire 2 [ r0 [1:0] $end
$var wire 1 H CRT_Start $end
$var parameter 32 \ INV0 $end
$var parameter 32 ] INV1 $end
$var parameter 32 ^ INV2 $end
$var parameter 32 _ INV3 $end
$var parameter 32 ` M $end
$var parameter 32 a M0 $end
$var parameter 32 b M1 $end
$var parameter 32 c M2 $end
$var parameter 32 d M3 $end
$var parameter 32 e OUT_WIDTH $end
$var parameter 32 f W0 $end
$var parameter 32 g W1 $end
$var parameter 32 h W2 $end
$var parameter 32 i W3 $end
$var reg 1 I CRT_Done $end
$var reg 16 j X_next [15:0] $end
$var reg 16 k X_out [15:0] $end
$var reg 1 l start_d $end
$var reg 10 m term0 [9:0] $end
$var reg 10 n term1 [9:0] $end
$var reg 11 o term2 [10:0] $end
$var reg 12 p term3 [11:0] $end
$var reg 13 q total [12:0] $end
$var reg 11 r total_mod [10:0] $end
$var reg 2 s x0_mod [1:0] $end
$var reg 3 t x1_mod [2:0] $end
$var reg 3 u x2_mod [2:0] $end
$var reg 4 v x3_mod [3:0] $end
$scope function norm_mod $end
$var integer 32 w m [31:0] $end
$var integer 32 x t [31:0] $end
$var integer 32 y x [31:0] $end
$upscope $end
$upscope $end
$scope module u_cu $end
$var wire 1 ) ALU_Done $end
$var wire 1 I CRT_Done $end
$var wire 3 z CU_state_dbg [2:0] $end
$var wire 1 , Encode_Done $end
$var wire 1 - MRC_Done $end
$var wire 1 { Recon_Mode $end
$var wire 1 & Start $end
$var wire 1 ' clk $end
$var wire 1 ( rst_n $end
$var wire 1 | recon_done_sel $end
$var parameter 3 } S_ALU $end
$var parameter 3 ~ S_DONE $end
$var parameter 3 !" S_ENCODE $end
$var parameter 3 "" S_IDLE $end
$var parameter 3 #" S_LOAD $end
$var parameter 3 $" S_OUT $end
$var parameter 3 %" S_RECON $end
$var reg 1 J ALU_EN $end
$var reg 1 H CRT_Start $end
$var reg 1 " Done $end
$var reg 1 D Encode_EN $end
$var reg 1 C Load_IN $end
$var reg 1 B MRC_Start $end
$var reg 1 A Out_EN $end
$var reg 3 &" next_state [2:0] $end
$var reg 3 '" state [2:0] $end
$upscope $end
$scope module u_enc_a $end
$var wire 1 D Encode_EN $end
$var wire 1 ' clk $end
$var wire 1 ( rst_n $end
$var wire 16 (" x [15:0] $end
$var wire 4 )" r3_next [3:0] $end
$var wire 3 *" r2_next [2:0] $end
$var wire 3 +" r1_next [2:0] $end
$var wire 2 ," r0_next [1:0] $end
$var parameter 32 -" M0 $end
$var parameter 32 ." M1 $end
$var parameter 32 /" M2 $end
$var parameter 32 0" M3 $end
$var parameter 32 1" W0 $end
$var parameter 32 2" W1 $end
$var parameter 32 3" W2 $end
$var parameter 32 4" W3 $end
$var parameter 32 5" WIDTH_IN $end
$var reg 1 F Encode_Done $end
$var reg 2 6" r0 [1:0] $end
$var reg 3 7" r1 [2:0] $end
$var reg 3 8" r2 [2:0] $end
$var reg 4 9" r3 [3:0] $end
$upscope $end
$scope module u_enc_b $end
$var wire 1 D Encode_EN $end
$var wire 1 ' clk $end
$var wire 1 ( rst_n $end
$var wire 16 :" x [15:0] $end
$var wire 4 ;" r3_next [3:0] $end
$var wire 3 <" r2_next [2:0] $end
$var wire 3 =" r1_next [2:0] $end
$var wire 2 >" r0_next [1:0] $end
$var parameter 32 ?" M0 $end
$var parameter 32 @" M1 $end
$var parameter 32 A" M2 $end
$var parameter 32 B" M3 $end
$var parameter 32 C" W0 $end
$var parameter 32 D" W1 $end
$var parameter 32 E" W2 $end
$var parameter 32 F" W3 $end
$var parameter 32 G" WIDTH_IN $end
$var reg 1 E Encode_Done $end
$var reg 2 H" r0 [1:0] $end
$var reg 3 I" r1 [2:0] $end
$var reg 3 J" r2 [2:0] $end
$var reg 4 K" r3 [3:0] $end
$upscope $end
$scope module u_slice0 $end
$var wire 1 J ALU_EN $end
$var wire 2 L" a [1:0] $end
$var wire 2 M" b [1:0] $end
$var wire 1 ' clk $end
$var wire 2 N" op_sel [1:0] $end
$var wire 1 ( rst_n $end
$var parameter 32 O" MODULUS $end
$var parameter 32 P" WIDTH $end
$var reg 1 7 ALU_Done $end
$var reg 1 Q" start_d $end
$var reg 2 R" y [1:0] $end
$var reg 2 S" y_next [1:0] $end
$var integer 32 T" tmp [31:0] $end
$upscope $end
$scope module u_slice1 $end
$var wire 1 J ALU_EN $end
$var wire 3 U" a [2:0] $end
$var wire 3 V" b [2:0] $end
$var wire 1 ' clk $end
$var wire 2 W" op_sel [1:0] $end
$var wire 1 ( rst_n $end
$var parameter 32 X" MODULUS $end
$var parameter 32 Y" WIDTH $end
$var reg 1 6 ALU_Done $end
$var reg 1 Z" start_d $end
$var reg 3 [" y [2:0] $end
$var reg 3 \" y_next [2:0] $end
$var integer 32 ]" tmp [31:0] $end
$upscope $end
$scope module u_slice2 $end
$var wire 1 J ALU_EN $end
$var wire 3 ^" a [2:0] $end
$var wire 3 _" b [2:0] $end
$var wire 1 ' clk $end
$var wire 2 `" op_sel [1:0] $end
$var wire 1 ( rst_n $end
$var parameter 32 a" MODULUS $end
$var parameter 32 b" WIDTH $end
$var reg 1 5 ALU_Done $end
$var reg 1 c" start_d $end
$var reg 3 d" y [2:0] $end
$var reg 3 e" y_next [2:0] $end
$var integer 32 f" tmp [31:0] $end
$upscope $end
$scope module u_slice3 $end
$var wire 1 J ALU_EN $end
$var wire 4 g" a [3:0] $end
$var wire 4 h" b [3:0] $end
$var wire 1 ' clk $end
$var wire 2 i" op_sel [1:0] $end
$var wire 1 ( rst_n $end
$var parameter 32 j" MODULUS $end
$var parameter 32 k" WIDTH $end
$var reg 1 4 ALU_Done $end
$var reg 1 l" start_d $end
$var reg 4 m" y [3:0] $end
$var reg 4 n" y_next [3:0] $end
$var integer 32 o" tmp [31:0] $end
$upscope $end
$upscope $end
$scope task run_test $end
$var reg 16 p" a [15:0] $end
$var reg 16 q" b [15:0] $end
$var reg 16 r" expected [15:0] $end
$var reg 128 s" name [127:0] $end
$var reg 2 t" op [1:0] $end
$upscope $end
$upscope $end
$enddefinitions $end
$comment Show the parameter values. $end
$dumpall
b100 k"
b1011 j"
b11 b"
b111 a"
b11 Y"
b101 X"
b10 P"
b11 O"
b10000 G"
b100 F"
b11 E"
b11 D"
b10 C"
b1011 B"
b111 A"
b101 @"
b11 ?"
b10000 5"
b100 4"
b11 3"
b11 2"
b10 1"
b1011 0"
b111 /"
b101 ."
b11 -"
b100 %"
b101 $"
b1 #"
b0 ""
b10 !"
b110 ~
b11 }
b100 i
b11 h
b11 g
b10 f
b10000 e
b1101001 d
b10100101 c
b11100111 b
b110000001 a
b10010000011 `
b10 _
b10 ^
b1 ]
b1 \
b10000 S
b100 R
b11 Q
b11 P
b10 O
b1011 N
b111 M
b101 L
b11 K
$end
#0
$dumpvars
bx t"
bx s"
bx r"
bx q"
bx p"
bx o"
bx n"
bx m"
xl"
bx i"
bx h"
bx g"
bx f"
bx e"
bx d"
xc"
bx `"
bx _"
bx ^"
bx ]"
bx \"
bx ["
xZ"
bx W"
bx V"
bx U"
bx T"
bx S"
bx R"
xQ"
bx N"
bx M"
bx L"
bx K"
bx J"
bx I"
bx H"
bx >"
bx ="
bx <"
bx ;"
bx :"
bx 9"
bx 8"
bx 7"
bx 6"
bx ,"
bx +"
bx *"
bx )"
bx ("
bx '"
b0 &"
x|
0{
bx z
bx y
bx x
bx w
bx v
bx u
bx t
bx s
bx r
bx q
bx p
bx o
bx n
bx m
xl
bx k
bx j
bx [
bx Z
bx Y
bx X
bx W
bx V
bx U
bx T
0J
xI
0H
bx G
xF
xE
0D
0C
0B
0A
bx @
bx ?
bx >
bx =
bx <
bx ;
bx :
bx 9
bx 8
x7
x6
x5
x4
bx 3
bx 2
bx 1
bx 0
bx /
b0 .
0-
x,
b0 +
b0 *
x)
0(
0'
0&
b0 %
b0 $
b0 #
0"
bx !
$end
#5000
0,
0)
0|
b0 G
b0 z
b0 '"
0F
0E
07
0Q"
06
0Z"
05
0c"
04
0l"
0l
0I
1'
#10000
0'
#15000
1'
#20000
0'
#25000
1'
#30000
0'
#35000
1'
#40000
0'
#45000
1'
#50000
1(
0'
#55000
1'
#60000
b111 $
b111 +
b1010 #
b1010 *
b100000101000100010001000101111100110001001100000101111100110111 s"
b10001 r"
b111 q"
b1010 p"
b0 t"
0'
#65000
1'
#70000
b1 &"
1&
0'
#75000
1C
b10 &"
b1 G
b1 z
b1 '"
1'
#80000
b10 &"
0&
0'
#85000
1D
0C
bx T"
bx S"
bx ]"
bx \"
bx f"
bx e"
bx o"
bx n"
b1 >"
b10 ="
b0 <"
b111 ;"
b1 ,"
b0 +"
b11 *"
b1010 )"
b10 G
b10 z
b10 '"
b0 V
b0 N"
b0 W"
b0 `"
b0 i"
b111 U
b111 :"
b1010 T
b1010 ("
1'
#90000
0'
#95000
b11 &"
1,
b110 o"
b110 n"
b11 f"
b11 e"
b10 ]"
b10 \"
b10 T"
b10 S"
1E
b111 8
b111 K"
b111 h"
b0 9
b0 J"
b0 _"
b10 :
b10 I"
b10 V"
b1 ;
b1 H"
b1 M"
1F
b1010 <
b1010 9"
b1010 g"
b11 =
b11 8"
b11 ^"
b0 >
b0 7"
b0 U"
b1 ?
b1 6"
b1 L"
1'
#100000
0'
#105000
1J
0D
b11 G
b11 z
b11 '"
1F
1E
1'
#110000
0'
#115000
b10001 j
b10001 r
b110110011010 q
b10011101100 p
b1111011110 o
b111001110 n
b1100000010 m
b110 v
b11 u
b10 t
b10 s
b10001 x
b110110011010 y
b10010000011 w
0,
b110 0
b110 X
b110 m"
1l"
b11 1
b11 Y
b11 d"
1c"
b10 2
b10 Z
b10 ["
1Z"
b10 3
b10 [
b10 R"
1Q"
0E
0F
1'
#120000
0'
#125000
b100 &"
1)
17
16
15
14
1'
#130000
0'
#135000
1H
0J
b100 G
b100 z
b100 '"
1'
#140000
0'
#145000
0Q"
0Z"
0c"
0l"
b10001 @
b10001 k
1l
1'
#150000
0'
#155000
b101 &"
1|
0)
1I
04
05
06
07
1'
#160000
0'
#165000
1A
0H
b110 &"
b101 G
b101 z
b101 '"
1'
#170000
0'
#175000
1"
0A
b0 &"
b10001 !
b10001 /
b10001 W
0l
b110 G
b110 z
b110 '"
1'
#180000
b100101100 $
b100101100 +
b1111101000 #
b1111101000 *
b100000101000100010001000101111101010111010100100100000101010000 s"
b10010001 r"
b100101100 q"
b1111101000 p"
0'
#185000
0"
0|
b0 G
b0 z
b0 '"
0I
1'
#190000
b1 &"
1&
0'
#195000
1C
b10 &"
b1 G
b1 z
b1 '"
1'
#200000
b10 &"
0&
0'
#205000
1D
0C
b0 >"
b0 ="
b110 <"
b11 ;"
b110 *"
b10 G
b10 z
b10 '"
b100101100 U
b100101100 :"
b1111101000 T
b1111101000 ("
1'
#210000
0'
